app/__init__.py
app/api.py
app/data_ingestion.py
app/models.py
app/monitoring.py
app/ranking.py
app/schema.py
app/storage.py
ai_feature_store-1.0.2.dist-info/METADATA
ai_feature_store-1.0.2.dist-info/WHEEL
ai_feature_store-1.0.2.dist-info/entry_points.txt
ai_feature_store-1.0.2.dist-info/top_level.txt
ai_feature_store-1.0.2.dist-info/RECORD
