Metadata-Version: 2.1
Name: ai-feature-store
Version: 1.0.2
Summary: A package for feature engineering and scalable storage with Google Bigtable.
Home-page: https://github.com/ashishodu2023/ai_feature_store
Author: Ashish Verma
Author-email: averm004@odu.edu
Classifier: Programming Language :: Python :: 3.11
Classifier: License :: OSI Approved :: MIT License
Classifier: Operating System :: OS Independent
Requires-Python: >=3.7
Requires-Dist: torch
Requires-Dist: fastapi
Requires-Dist: uvicorn
Requires-Dist: scikit-learn
Requires-Dist: pandas
Requires-Dist: google-cloud-bigtable
Requires-Dist: prometheus-client
